<?xml version="1.0" encoding="utf-8"?>
<annotation>
   <folder>VOC2017</folder>
   <filename>actions3_003468.jpg</filename>
   <source>
      <database>The VOC2007 Database</database>
      <annotation>PASCAL VOC2007</annotation>
      <image>Unspecified</image>
      <flickrid>Unspecified</flickrid>
   </source>
   <owner>
      <flickrid>Unspecified</flickrid>
      <name>Unspecified</name>
   </owner>
   <size>
      <width>960</width>
      <height>540</height>
      <depth>3</depth>
   </size>
   <segmented>0</segmented>
   <object>
      <name>person</name>
      <pose>Unspecified</pose>
      <truncated>0</truncated>
      <difficult>0</difficult>
      <bndbox>
         <xmin>395</xmin>
         <ymin>490</ymin>
         <xmax>448</xmax>
         <ymax>563</ymax>
      </bndbox>
   </object>
   <object>
      <name>person</name>
      <pose>Unspecified</pose>
      <truncated>0</truncated>
      <difficult>0</difficult>
      <bndbox>
         <xmin>445</xmin>
         <ymin>316</ymin>
         <xmax>492</xmax>
         <ymax>386</ymax>
      </bndbox>
   </object>
   <object>
      <name>person</name>
      <pose>Unspecified</pose>
      <truncated>0</truncated>
      <difficult>0</difficult>
      <bndbox>
         <xmin>356</xmin>
         <ymin>373</ymin>
         <xmax>397</xmax>
         <ymax>436</ymax>
      </bndbox>
   </object>
   <object>
      <name>person</name>
      <pose>Unspecified</pose>
      <truncated>0</truncated>
      <difficult>0</difficult>
      <bndbox>
         <xmin>360</xmin>
         <ymin>283</ymin>
         <xmax>403</xmax>
         <ymax>345</ymax>
      </bndbox>
   </object>
   <object>
      <name>person</name>
      <pose>Unspecified</pose>
      <truncated>0</truncated>
      <difficult>0</difficult>
      <bndbox>
         <xmin>442</xmin>
         <ymin>357</ymin>
         <xmax>487</xmax>
         <ymax>417</ymax>
      </bndbox>
   </object>
</annotation>