<?xml version="1.0" encoding="utf-8"?>
<annotation>
   <folder>VOC2017</folder>
   <filename>actions3_001414.jpg</filename>
   <source>
      <database>The VOC2007 Database</database>
      <annotation>PASCAL VOC2007</annotation>
      <image>Unspecified</image>
      <flickrid>Unspecified</flickrid>
   </source>
   <owner>
      <flickrid>Unspecified</flickrid>
      <name>Unspecified</name>
   </owner>
   <size>
      <width>960</width>
      <height>540</height>
      <depth>3</depth>
   </size>
   <segmented>0</segmented>
   <object>
      <name>person</name>
      <pose>Unspecified</pose>
      <truncated>0</truncated>
      <difficult>0</difficult>
      <bndbox>
         <xmin>566</xmin>
         <ymin>269</ymin>
         <xmax>619</xmax>
         <ymax>342</ymax>
      </bndbox>
   </object>
   <object>
      <name>person</name>
      <pose>Unspecified</pose>
      <truncated>0</truncated>
      <difficult>0</difficult>
      <bndbox>
         <xmin>758</xmin>
         <ymin>219</ymin>
         <xmax>805</xmax>
         <ymax>289</ymax>
      </bndbox>
   </object>
   <object>
      <name>person</name>
      <pose>Unspecified</pose>
      <truncated>0</truncated>
      <difficult>0</difficult>
      <bndbox>
         <xmin>501</xmin>
         <ymin>83</ymin>
         <xmax>549</xmax>
         <ymax>150</ymax>
      </bndbox>
   </object>
   <object>
      <name>person</name>
      <pose>Unspecified</pose>
      <truncated>0</truncated>
      <difficult>0</difficult>
      <bndbox>
         <xmin>744</xmin>
         <ymin>385</ymin>
         <xmax>785</xmax>
         <ymax>448</ymax>
      </bndbox>
   </object>
   <object>
      <name>person</name>
      <pose>Unspecified</pose>
      <truncated>0</truncated>
      <difficult>0</difficult>
      <bndbox>
         <xmin>803</xmin>
         <ymin>435</ymin>
         <xmax>846</xmax>
         <ymax>497</ymax>
      </bndbox>
   </object>
   <object>
      <name>person</name>
      <pose>Unspecified</pose>
      <truncated>0</truncated>
      <difficult>0</difficult>
      <bndbox>
         <xmin>74</xmin>
         <ymin>404</ymin>
         <xmax>108</xmax>
         <ymax>460</ymax>
      </bndbox>
   </object>
</annotation>