<?xml version="1.0" encoding="utf-8"?>
<annotation>
   <folder>VOC2017</folder>
   <filename>actions3_001057.jpg</filename>
   <source>
      <database>The VOC2007 Database</database>
      <annotation>PASCAL VOC2007</annotation>
      <image>Unspecified</image>
      <flickrid>Unspecified</flickrid>
   </source>
   <owner>
      <flickrid>Unspecified</flickrid>
      <name>Unspecified</name>
   </owner>
   <size>
      <width>960</width>
      <height>540</height>
      <depth>3</depth>
   </size>
   <segmented>0</segmented>
   <object>
      <name>person</name>
      <pose>Unspecified</pose>
      <truncated>0</truncated>
      <difficult>0</difficult>
      <bndbox>
         <xmin>263</xmin>
         <ymin>351</ymin>
         <xmax>316</xmax>
         <ymax>424</ymax>
      </bndbox>
   </object>
   <object>
      <name>person</name>
      <pose>Unspecified</pose>
      <truncated>0</truncated>
      <difficult>0</difficult>
      <bndbox>
         <xmin>535</xmin>
         <ymin>286</ymin>
         <xmax>594</xmax>
         <ymax>367</ymax>
      </bndbox>
   </object>
   <object>
      <name>person</name>
      <pose>Unspecified</pose>
      <truncated>0</truncated>
      <difficult>0</difficult>
      <bndbox>
         <xmin>428</xmin>
         <ymin>313</ymin>
         <xmax>476</xmax>
         <ymax>380</ymax>
      </bndbox>
   </object>
   <object>
      <name>person</name>
      <pose>Unspecified</pose>
      <truncated>0</truncated>
      <difficult>0</difficult>
      <bndbox>
         <xmin>539</xmin>
         <ymin>437</ymin>
         <xmax>580</xmax>
         <ymax>500</ymax>
      </bndbox>
   </object>
   <object>
      <name>person</name>
      <pose>Unspecified</pose>
      <truncated>0</truncated>
      <difficult>0</difficult>
      <bndbox>
         <xmin>356</xmin>
         <ymin>477</ymin>
         <xmax>399</xmax>
         <ymax>539</ymax>
      </bndbox>
   </object>
</annotation>