<?xml version="1.0" encoding="utf-8"?>
<annotation>
   <folder>VOC2017</folder>
   <filename>actions3_001207.jpg</filename>
   <source>
      <database>The VOC2007 Database</database>
      <annotation>PASCAL VOC2007</annotation>
      <image>Unspecified</image>
      <flickrid>Unspecified</flickrid>
   </source>
   <owner>
      <flickrid>Unspecified</flickrid>
      <name>Unspecified</name>
   </owner>
   <size>
      <width>960</width>
      <height>540</height>
      <depth>3</depth>
   </size>
   <segmented>0</segmented>
   <object>
      <name>person</name>
      <pose>Unspecified</pose>
      <truncated>0</truncated>
      <difficult>0</difficult>
      <bndbox>
         <xmin>105</xmin>
         <ymin>267</ymin>
         <xmax>158</xmax>
         <ymax>340</ymax>
      </bndbox>
   </object>
   <object>
      <name>person</name>
      <pose>Unspecified</pose>
      <truncated>0</truncated>
      <difficult>0</difficult>
      <bndbox>
         <xmin>412</xmin>
         <ymin>255</ymin>
         <xmax>454</xmax>
         <ymax>314</ymax>
      </bndbox>
   </object>
   <object>
      <name>person</name>
      <pose>Unspecified</pose>
      <truncated>0</truncated>
      <difficult>0</difficult>
      <bndbox>
         <xmin>262</xmin>
         <ymin>251</ymin>
         <xmax>310</xmax>
         <ymax>318</ymax>
      </bndbox>
   </object>
   <object>
      <name>person</name>
      <pose>Unspecified</pose>
      <truncated>0</truncated>
      <difficult>0</difficult>
      <bndbox>
         <xmin>367</xmin>
         <ymin>407</ymin>
         <xmax>408</xmax>
         <ymax>470</ymax>
      </bndbox>
   </object>
   <object>
      <name>person</name>
      <pose>Unspecified</pose>
      <truncated>0</truncated>
      <difficult>0</difficult>
      <bndbox>
         <xmin>214</xmin>
         <ymin>403</ymin>
         <xmax>257</xmax>
         <ymax>465</ymax>
      </bndbox>
   </object>
</annotation>