<?xml version="1.0" encoding="utf-8"?>
<annotation>
   <folder>VOC2017</folder>
   <filename>actions3_005206.jpg</filename>
   <source>
      <database>The VOC2007 Database</database>
      <annotation>PASCAL VOC2007</annotation>
      <image>Unspecified</image>
      <flickrid>Unspecified</flickrid>
   </source>
   <owner>
      <flickrid>Unspecified</flickrid>
      <name>Unspecified</name>
   </owner>
   <size>
      <width>960</width>
      <height>540</height>
      <depth>3</depth>
   </size>
   <segmented>0</segmented>
   <object>
      <name>person</name>
      <pose>Unspecified</pose>
      <truncated>0</truncated>
      <difficult>0</difficult>
      <bndbox>
         <xmin>613</xmin>
         <ymin>423</ymin>
         <xmax>667</xmax>
         <ymax>491</ymax>
      </bndbox>
   </object>
   <object>
      <name>person</name>
      <pose>Unspecified</pose>
      <truncated>0</truncated>
      <difficult>0</difficult>
      <bndbox>
         <xmin>493</xmin>
         <ymin>414</ymin>
         <xmax>542</xmax>
         <ymax>477</ymax>
      </bndbox>
   </object>
   <object>
      <name>person</name>
      <pose>Unspecified</pose>
      <truncated>0</truncated>
      <difficult>0</difficult>
      <bndbox>
         <xmin>364</xmin>
         <ymin>330</ymin>
         <xmax>402</xmax>
         <ymax>393</ymax>
      </bndbox>
   </object>
   <object>
      <name>person</name>
      <pose>Unspecified</pose>
      <truncated>0</truncated>
      <difficult>0</difficult>
      <bndbox>
         <xmin>295</xmin>
         <ymin>468</ymin>
         <xmax>334</xmax>
         <ymax>524</ymax>
      </bndbox>
   </object>
   <object>
      <name>person</name>
      <pose>Unspecified</pose>
      <truncated>0</truncated>
      <difficult>0</difficult>
      <bndbox>
         <xmin>490</xmin>
         <ymin>495</ymin>
         <xmax>529</xmax>
         <ymax>550</ymax>
      </bndbox>
   </object>
</annotation>